{"href":"https://weighttraining.guide/exercises/barbell-one-leg-hip-thrust/","Target muscle":" Gluteus Maximus","Synergists":" Quadriceps (Vastus Lateralis, Vastus Medialis, Vastus Intermedius, Rectus Femoris)","Dynamic stabilizers":" Hamstrings","Mechanics":" Isolation","Force":" Push","name":"Barbell one-leg hip thrust","image":"data:image/svg+xml,%3Csvg%20xmlns=%22http://www.w3.org/2000/svg%22%20width=%221320%22%20height=%22880%22%3E%3C/svg%3E","tags":["barbell","gluteus maximus","isolation","push","quadriceps"]}