{"href":"https://weighttraining.guide/exercises/seated-neutral-grip-dumbbell-overhead-press/","Target muscle":" Anterior Deltoid","Synergists":" Lateral Deltoid, Clavicular (Upper) Pectoralis Major, Triceps Brachii, Middle and Lower Trapezius, Serratus Anterior","Dynamic stabilizers":" Biceps Brachii (not highlighted in illustration), Triceps Brachii (long head)","Mechanics":" Compound","Force":" Push","name":"Seated elbows-in dumbbell overhead press","image":"https://cdn-0.weighttraining.guide/wp-content/uploads/2017/08/seated-neutral-grip-dumbbell-overhead-press-resized.png?ezimgfmt=ng%3Awebp%2Fngcb4","tags":["anterior deltoid","compound","dumbbells","lateral deltoid","middle and lower trapezius","push","serratus anterior","triceps brachii","upper pectoralis major"]}